sigil_pipeline/__init__.py
sigil_pipeline/analysis_cache.py
sigil_pipeline/analyzer.py
sigil_pipeline/api_tracker.py
sigil_pipeline/ast_patterns.py
sigil_pipeline/chunker.py
sigil_pipeline/config.py
sigil_pipeline/converters.py
sigil_pipeline/crawler.py
sigil_pipeline/dataset_builder.py
sigil_pipeline/dataset_splitter.py
sigil_pipeline/environment.py
sigil_pipeline/exporter.py
sigil_pipeline/filter.py
sigil_pipeline/format_validator.py
sigil_pipeline/github_miner.py
sigil_pipeline/gpu_setup.py
sigil_pipeline/main.py
sigil_pipeline/observability.py
sigil_pipeline/output_validator.py
sigil_pipeline/prompt_templates.py
sigil_pipeline/sandbox.py
sigil_pipeline/schema.py
sigil_pipeline/task_generator.py
sigil_pipeline/task_generator_llm.py
sigil_pipeline/telemetry.py
sigil_pipeline/usage_analyzer.py
sigil_pipeline/utils.py
sigil_pipeline/cli/__init__.py
sigil_pipeline/cli/ecosystem.py
sigil_pipeline-2.6.2.dist-info/licenses/LICENSE
sigil_pipeline-2.6.2.dist-info/METADATA
sigil_pipeline-2.6.2.dist-info/WHEEL
sigil_pipeline-2.6.2.dist-info/entry_points.txt
sigil_pipeline-2.6.2.dist-info/top_level.txt
sigil_pipeline-2.6.2.dist-info/RECORD
